{
	"info": {
		"_postman_id": "aed804ea-8856-4170-b427-ad3e9bbd471a",
		"name": "ListaDois",
		"schema": "https://schema.getpostman.com/json/collection/v2.1.0/collection.json",
		"_exporter_id": "39345897"
	},
	"item": [
		{
			"name": "Get",
			"item": [
				{
					"name": "RetornaTudo",
					"event": [
						{
							"listen": "test",
							"script": {
								"exec": [
									"pm.test(\"Deve retornar status 200 OK\", function () {\r",
									"    pm.response.to.have.status(200);\r",
									"});\r",
									"\r",
									"pm.test(\"O corpo da resposta deve ser uma lista de posts\", function () {\r",
									"    pm.response.to.have.jsonBody();\r",
									"    pm.expect(pm.response.json()).to.be.an('array');\r",
									"});"
								],
								"type": "text/javascript",
								"packages": {}
							}
						}
					],
					"request": {
						"method": "GET",
						"header": [],
						"url": {
							"raw": "https://jsonplaceholder.typicode.com/posts",
							"protocol": "https",
							"host": [
								"jsonplaceholder",
								"typicode",
								"com"
							],
							"path": [
								"posts"
							]
						}
					},
					"response": []
				},
				{
					"name": "RetornaErro",
					"event": [
						{
							"listen": "test",
							"script": {
								"exec": [
									"pm.test(\"Deve retornar status 404 Not Found\", function () {\r",
									"    pm.response.to.have.status(404);\r",
									"});"
								],
								"type": "text/javascript",
								"packages": {}
							}
						}
					],
					"request": {
						"method": "GET",
						"header": [],
						"url": {
							"raw": "https://jsonplaceholder.typicode.com/posts/999999",
							"protocol": "https",
							"host": [
								"jsonplaceholder",
								"typicode",
								"com"
							],
							"path": [
								"posts",
								"999999"
							]
						}
					},
					"response": []
				}
			]
		},
		{
			"name": "Post",
			"item": [
				{
					"name": "CriarPost",
					"event": [
						{
							"listen": "test",
							"script": {
								"exec": [
									"pm.test(\"Deve retornar status 201 Created\", function () {\r",
									"    pm.response.to.have.status(201);\r",
									"});"
								],
								"type": "text/javascript",
								"packages": {}
							}
						}
					],
					"request": {
						"method": "POST",
						"header": [],
						"url": {
							"raw": "https://jsonplaceholder.typicode.com/posts",
							"protocol": "https",
							"host": [
								"jsonplaceholder",
								"typicode",
								"com"
							],
							"path": [
								"posts"
							]
						}
					},
					"response": []
				},
				{
					"name": "PostErro",
					"event": [
						{
							"listen": "test",
							"script": {
								"exec": [
									"pm.test(\"Deve retornar status 404 Not Found\", function () {\r",
									"    pm.response.to.have.status(404);\r",
									"});"
								],
								"type": "text/javascript",
								"packages": {}
							}
						}
					],
					"request": {
						"method": "POST",
						"header": [],
						"body": {
							"mode": "raw",
							"raw": "{\r\n    \"title\": \"Post Inexistente\",\r\n    \"body\": \"Este post não existe.\",\r\n    \"userId\": 1\r\n}",
							"options": {
								"raw": {
									"language": "json"
								}
							}
						},
						"url": {
							"raw": "https://jsonplaceholder.typicode.com/posts/999999",
							"protocol": "https",
							"host": [
								"jsonplaceholder",
								"typicode",
								"com"
							],
							"path": [
								"posts",
								"999999"
							]
						}
					},
					"response": []
				}
			]
		},
		{
			"name": "Put",
			"item": [
				{
					"name": "RetornaId1",
					"event": [
						{
							"listen": "test",
							"script": {
								"exec": [
									"pm.test(\"Deve retornar status 200 OK\", function () {\r",
									"    pm.response.to.have.status(200);\r",
									"});"
								],
								"type": "text/javascript",
								"packages": {}
							}
						}
					],
					"request": {
						"method": "PUT",
						"header": [],
						"url": {
							"raw": "https://jsonplaceholder.typicode.com/posts/1",
							"protocol": "https",
							"host": [
								"jsonplaceholder",
								"typicode",
								"com"
							],
							"path": [
								"posts",
								"1"
							]
						}
					},
					"response": []
				}
			]
		},
		{
			"name": "Delete",
			"item": [
				{
					"name": "Delete",
					"event": [
						{
							"listen": "test",
							"script": {
								"exec": [
									"pm.test(\"Deve retornar status 200 OK\", function () {\r",
									"    pm.response.to.have.status(200);\r",
									"});"
								],
								"type": "text/javascript",
								"packages": {}
							}
						}
					],
					"request": {
						"method": "DELETE",
						"header": [],
						"url": {
							"raw": "https://jsonplaceholder.typicode.com/posts/1",
							"protocol": "https",
							"host": [
								"jsonplaceholder",
								"typicode",
								"com"
							],
							"path": [
								"posts",
								"1"
							]
						}
					},
					"response": []
				}
			]
		}
	]
}